yapatch/__init__.py
yapatch/main.py
yapatch/patch.py
yapatch-0.0.2.dist-info/METADATA
yapatch-0.0.2.dist-info/WHEEL
yapatch-0.0.2.dist-info/entry_points.txt
yapatch-0.0.2.dist-info/top_level.txt
yapatch-0.0.2.dist-info/RECORD
